riffaraffa/__init__.py
riffaraffa/cli.py
riffaraffa/config.py
riffaraffa/models.py
riffaraffa/riffaraffa.py
riffaraffa-0.2.0.dist-info/AUTHORS.rst
riffaraffa-0.2.0.dist-info/LICENSE
riffaraffa-0.2.0.dist-info/METADATA
riffaraffa-0.2.0.dist-info/WHEEL
riffaraffa-0.2.0.dist-info/entry_points.txt
riffaraffa-0.2.0.dist-info/top_level.txt
riffaraffa-0.2.0.dist-info/RECORD
