Metadata-Version: 2.1
Name: riffaraffa
Version: 0.2.0
Summary: La riffa e la raffa python package.
Home-page: https://github.com/robertopreste/riffaraffa
Author: Roberto Preste
Author-email: robertopreste@gmail.com
License: MIT license
Keywords: riffaraffa
Platform: UNKNOWN
Classifier: Development Status :: 2 - Pre-Alpha
Classifier: Intended Audience :: Developers
Classifier: License :: OSI Approved :: MIT License
Classifier: Natural Language :: English
Classifier: Programming Language :: Python :: 3
Classifier: Programming Language :: Python :: 3.6
Classifier: Programming Language :: Python :: 3.7
Requires-Dist: Click
Requires-Dist: sqlalchemy
